{
  "project_info": {
    "project_number": "855117849518",
    "project_id": "jjangu-diary",
    "storage_bucket": "jjangu-diary.appspot.com"
  },
  "client": [
    {
      "client_info": {
        "mobilesdk_app_id": "1:855117849518:android:778f25a77bc3352613de3f",
        "android_client_info": {
          "package_name": "com.example.jjangu_diary"
        }
      },
      "oauth_client": [],
      "api_key": [
        {
          "current_key": "AIzaSyAScwLeBvtCJ6S45pAvgeBft9Sbn4w4tZE"
        }
      ],
      "services": {
        "appinvite_service": {
          "other_platform_oauth_client": []
        }
      }
    }
  ],
  "configuration_version": "1"
}